sensorpush_api/__init__.py
sensorpush_api/api_client.py
sensorpush_api/api_response.py
sensorpush_api/configuration.py
sensorpush_api/exceptions.py
sensorpush_api/py.typed
sensorpush_api/rest.py
sensorpush_api/api/__init__.py
sensorpush_api/api/api_api.py
sensorpush_api/models/__init__.py
sensorpush_api/models/access_token_request.py
sensorpush_api/models/access_token_response.py
sensorpush_api/models/authorize_request.py
sensorpush_api/models/authorize_response.py
sensorpush_api/models/error.py
sensorpush_api/models/gateway.py
sensorpush_api/models/gateways_request.py
sensorpush_api/models/list_response.py
sensorpush_api/models/report_listing.py
sensorpush_api/models/reports_request.py
sensorpush_api/models/sample.py
sensorpush_api/models/samples.py
sensorpush_api/models/samples_request.py
sensorpush_api/models/sensor.py
sensorpush_api/models/sensor_alerts.py
sensorpush_api/models/sensor_alerts_humidity.py
sensorpush_api/models/sensor_alerts_temperature.py
sensorpush_api/models/sensor_calibration.py
sensorpush_api/models/sensors_request.py
sensorpush_api/models/status.py
sensorpush_api/models/tags.py
sensorpush_api/models/tags_request.py
sensorpush_api/models/tags_response.py
sensorpush_api/models/token_request.py
sensorpush_api/models/token_response.py
sensorpush_api-2.1.2.dist-info/licenses/LICENSE
test/__init__.py
test/test_access_token_request.py
test/test_access_token_response.py
test/test_api_api.py
test/test_authorize_request.py
test/test_authorize_response.py
test/test_error.py
test/test_gateway.py
test/test_gateways_request.py
test/test_list_response.py
test/test_report_listing.py
test/test_reports_request.py
test/test_sample.py
test/test_samples.py
test/test_samples_request.py
test/test_sensor.py
test/test_sensor_alerts.py
test/test_sensor_alerts_humidity.py
test/test_sensor_alerts_temperature.py
test/test_sensor_calibration.py
test/test_sensors_request.py
test/test_status.py
test/test_tags.py
test/test_tags_request.py
test/test_tags_response.py
test/test_token_request.py
test/test_token_response.py
sensorpush_api-2.1.2.dist-info/METADATA
sensorpush_api-2.1.2.dist-info/WHEEL
sensorpush_api-2.1.2.dist-info/top_level.txt
sensorpush_api-2.1.2.dist-info/RECORD
