Metadata-Version: 2.4
Name: sensorpush-api
Version: 2.1.2
Summary: SensorPush Public API
Home-page: https://github.com/sstallion/sensorpush-api
Author: Steven Stallion
Author-email: sstallion@gmail.com
License: BSD-2-Clause
Keywords: sensorpush swagger
Classifier: Development Status :: 5 - Production/Stable
Classifier: Environment :: Web Environment
Classifier: Intended Audience :: Developers
Classifier: License :: OSI Approved :: BSD License
Classifier: Operating System :: OS Independent
Classifier: Programming Language :: Python
Classifier: Programming Language :: Python :: 3
Classifier: Programming Language :: Python :: 3.8
Classifier: Programming Language :: Python :: 3.9
Classifier: Programming Language :: Python :: 3.10
Classifier: Programming Language :: Python :: 3.11
Classifier: Programming Language :: Python :: 3.12
Classifier: Topic :: Internet :: WWW/HTTP
Classifier: Topic :: Software Development :: Libraries
Classifier: Topic :: Software Development :: Libraries :: Python Modules
License-File: LICENSE
Requires-Dist: python_dateutil>=2.5.3
Requires-Dist: urllib3<2.1.0,>=1.25.3
Requires-Dist: pydantic>=1.10.5
Requires-Dist: aiohttp>=3.0.0
Provides-Extra: test
Requires-Dist: pytest~=7.1.3; extra == "test"
Requires-Dist: pytest-cov>=2.8.1; extra == "test"
Requires-Dist: pytest-randomly>=3.12.0; extra == "test"
Provides-Extra: release
Requires-Dist: build>=0.3.0; extra == "release"
Dynamic: author
Dynamic: author-email
Dynamic: classifier
Dynamic: description
Dynamic: description-content-type
Dynamic: home-page
Dynamic: keywords
Dynamic: license
Dynamic: license-file
Dynamic: provides-extra
Dynamic: requires-dist
Dynamic: summary
